odoo8_addon_web_offline_warning-8.0.1.0.0.99.dev12-py3.8-nspkg.pth
odoo_addons/web_offline_warning/README.rst
odoo_addons/web_offline_warning/__init__.py
odoo_addons/web_offline_warning/__openerp__.py
odoo_addons/web_offline_warning/i18n/ar.po
odoo_addons/web_offline_warning/i18n/de.po
odoo_addons/web_offline_warning/i18n/es.po
odoo_addons/web_offline_warning/i18n/eu.po
odoo_addons/web_offline_warning/i18n/fi.po
odoo_addons/web_offline_warning/i18n/fr.po
odoo_addons/web_offline_warning/i18n/hr.po
odoo_addons/web_offline_warning/i18n/it.po
odoo_addons/web_offline_warning/i18n/pt_BR.po
odoo_addons/web_offline_warning/i18n/sl.po
odoo_addons/web_offline_warning/i18n/tr.po
odoo_addons/web_offline_warning/i18n/web_offline_warning.pot
odoo_addons/web_offline_warning/static/description/icon.png
odoo_addons/web_offline_warning/static/src/js/web_offline_warning.js
odoo_addons/web_offline_warning/views/assets.xml
odoo8_addon_web_offline_warning-8.0.1.0.0.99.dev12.dist-info/METADATA
odoo8_addon_web_offline_warning-8.0.1.0.0.99.dev12.dist-info/WHEEL
odoo8_addon_web_offline_warning-8.0.1.0.0.99.dev12.dist-info/namespace_packages.txt
odoo8_addon_web_offline_warning-8.0.1.0.0.99.dev12.dist-info/top_level.txt
odoo8_addon_web_offline_warning-8.0.1.0.0.99.dev12.dist-info/RECORD
